sql2sql/objects.py
sql2sql-0.0.1.dist-info/DESCRIPTION.rst
sql2sql-0.0.1.dist-info/METADATA
sql2sql-0.0.1.dist-info/RECORD
sql2sql-0.0.1.dist-info/WHEEL
sql2sql-0.0.1.dist-info/metadata.json
sql2sql-0.0.1.dist-info/top_level.txt
